[1,["45nNvFiPtFiLh+anVBAxqK@6c48a","76tdu0f6xNBqPuTsIub2b6@6c48a","3eUBug7tpEe4tDm6Dppbi9@6c48a","2ewRRY+FVJeLFN8+1c9pf6"],["mainTexture","roughnessMap","occlusionMap","emissiveScaleMap","emissiveMap","_effectAsset"],[["cc.Material",["_states","_defines","_props"],1,12]],[[0,0,1,2,3]],[[0,[{"rasterizerState":{},"depthStencilState":{},"blendState":{"targets":[{}]}},{"rasterizerState":{},"depthStencilState":{},"blendState":{"targets":[{}]}},{"rasterizerState":{},"depthStencilState":{},"blendState":{"targets":[{}]}},{"rasterizerState":{},"depthStencilState":{},"blendState":{"targets":[{}]}}],[{"USE_ROUGHNESS_MAP":true,"USE_OCCLUSION_MAP":true,"USE_EMISSIVE_MAP":true,"USE_EMISSIVESCALE_MAP":true},{},{},{}],[[[{"roughness":0.5,"metallic":0,"emissiveScale":0,"alphaThreshold":1},"mainColor",8,[4,4289374890],"emissive",8,[4,4294967295],"mainTexture",6,0,"roughnessMap",6,1,"occlusionMap",6,2,"emissiveScaleMap",6,3,"emissiveMap",6,4],{},{},{}],11,0,0,0]]],0,0,[0,0,0,0,0,0],[0,1,2,3,4,5],[0,1,1,0,2,3]]
